PART1/Part1/Or.v
/*
CO224: Computer Architecture 
Lab 05: Part-1				 
The Sub Module OR			 
Group - 12					 
*/

// OR module definition
module OR(DATA1, DATA2, RESULT);

	// Begin port declaration
	input [7:0] DATA1, DATA2; // Declare inputs
	
	output [7:0] RESULT; // Declare output
	// End of port declaration
	
	// Using continuous assignment assign DATA1 | DATA2 to RESULT (Unit's delay = #1)
	assign #1 RESULT = DATA1 | DATA2;
	
endmodule

PART1/Part4/And.v
/*
CO224: Computer Architecture 
Lab 05: Part-1				 
The Sub Module AND			 
Group - 12					 
*/

// AND module definition
module AND(DATA1, DATA2, RESULT);

	// Begin port declaration
	input [7:0] DATA1, DATA2; // Declare inputs
	
	output [7:0] RESULT; // Declare output
	// End of port declaration

	// Using continuous assignment assign DATA1 & DATA2 to RESULT (Unit's delay = #1)
	assign #1 RESULT = DATA1 & DATA2;
	
endmodule

PART1/Part2/Add.v
/*
CO224: Computer Architecture 
Lab 05: Part-1				 
The Sub Module ADD			 
Group - 12					 
*/

// ADD module definition
module ADD(DATA1, DATA2, RESULT);

	// Begin port declaration
	input [7:0] DATA1, DATA2; // Declare inputs
	
	output [7:0] RESULT; // Declare output
	// End of port declaration
	
	// Using continuous assignment assign DATA1 + DATA2 to RESULT (Unit's delay = #2)
	assign #2 RESULT = DATA1 + DATA2;
	
endmodule

PART2/Part1/Forward.v
/*
CO224: Computer Architecture 
Lab 05: Part-1				 
The Sub Module FORWARD			 
Group - 12					 
*/

// FORWARD module definition
module FORWARD(DATA2, RESULT);

	// Begin port declaration
	input [7:0] DATA2; // Declare inputs
	
	output [7:0] RESULT; // Declare output
	// End of port declaration
	
	// Using continuous assignment assign DATA2 to RESULT (Unit's delay = #1)
	assign #1 RESULT = DATA2;

endmodule

PART1/Part1/Alu.v
/*
CO224: Computer Architecture 
Lab 05: Part-1				 
The ALU Module			 
Group - 12					 
*/

// Importing modules
`include "Add.v"
`include "And.v"
`include "Forward.v"
`include "Or.v"

// ALU module definition
module alu(DATA1, DATA2, RESULT, SELECT);
	
	// Begin port declaration

	// Declare inputs
	input [7:0] DATA1, DATA2;
	input [2:0] SELECT;
	
	// Declare output
	output reg [7:0] RESULT;

	// End of port declaration
	
	// Wires for outputs of the distinct functional units
	wire [7:0] Forward_Out, Add_Out, And_Out, Or_Out;
	
	
	// Instantiation of modules
	FORWARD forward1(DATA2, Forward_Out); // Instantiate a FORWARD object
	ADD add1(DATA1, DATA2, Add_Out); // Instantiate an ADD object
	AND and1(DATA1, DATA2, And_Out); // Instantiate an AND object
	OR or1(DATA1, DATA2, Or_Out); // Instantiate an OR object
	
	
	// A MUX to pick one of the functional units, outputs and send it to RESULT based on the SELECT value
	always @ (Forward_Out, Add_Out, And_Out, Or_Out, SELECT)	
	begin

		case (SELECT)	
			3'b000 :	RESULT = Forward_Out;	//SELECT = 0 : FORWARD
			3'b001 :	RESULT = Add_Out;		//SELECT = 1 : ADD
			3'b010 :	RESULT = And_Out;		//SELECT = 2 : AND
			3'b011 :	RESULT = Or_Out;		//SELECT = 3 : OR
			3'b1xx :	RESULT = 8'bxxxxxxxx;	//SELECT = 1xx : x
		endcase

	end

endmodule

PART1/Part3/Mux.v
/*
CO224: Computer Architecture 
Lab 05: Part-3				 
The Sub Module Mux			 
Group - 12					 
*/

// mux module definition
module mux(IN1, IN2, SELECT, OUT);

	// Begin port declaration
	input [7:0] IN1, IN2;   // Declare inputs
	input SELECT;
	output reg [7:0] OUT;   // Declare output
    // End of port declaration
	
	// Mux should update output value if any changes happened in inputs
	always @ (IN1, IN2, SELECT)
	begin
		if (SELECT == 1'b0)		//If SELECT is Law, switch to 1st input
		begin
			OUT = IN1;
		end
		else					//If SELECT is High, switch to 2nd input
		begin
			OUT = IN2;
		end
	end

endmodule

PART1/Part3/2sComp.v
/*
CO224: Computer Architecture 
Lab 05: Part-3				 
The Sub Module 2sComp			 
Group - 12					 
*/

// twosComp module definition
module TwosComp(OPERAND, RESULT);

	// Begin port declaration
    input [7:0] OPERAND;    // Declare input
	output [7:0] RESULT;    // Declare output
    // End of port declaration
	
	// Combinational logic to getting the 2's complement of the OPERAND and assigning it to the RESULT
	assign #1 RESULT = ~OPERAND + 1;

endmodule

PART1/Part3/Reg_file.v
/*
CO224: Computer Architecture 
Lab 05: Part-2				 
Register File				 
Group - 12					 
*/

// Definition of the register file
module reg_file(IN,OUT1,OUT2,INADDRESS,OUT1ADDRESS,OUT2ADDRESS, WRITE, CLK, RESET);

	// Begin port declaration
	input [7:0] IN; // 8-bit input for input the data
	input [2:0] INADDRESS, OUT1ADDRESS, OUT2ADDRESS; // To store the register numbers of input & output data
	
	input WRITE, CLK, RESET; // Inputs for WRITEENABLE CLOCK and RESET signals
	
	output [7:0] OUT1, OUT2; // 8-bit outputs for output the data(Should be read asynchronously)
	// End of port declaration
	
	// An array of 8*8-bit registers
	reg [7:0] REGISTER [7:0];

	integer i; // This variable will used to iterate throught the foor loop
	
	//Reads data from registers asynchronously
	// Using continuous assignment assign OUT1 and OUT2 for OUT1ADRESS and OUT2ADDRESS registers respectively (Unit's delay = #2)
	assign #2 OUT1 = REGISTER[OUT1ADDRESS];		
	assign #2 OUT2 = REGISTER[OUT2ADDRESS];		
	
	// Write and Reset registers synchronously

	always @ (posedge CLK)
	begin

		if (RESET == 1'b1) // If the RESET signal is HIGH, registers must be cleared
		begin
		
			#1 for (i = 0; i < 8; i = i + 1) // Iterating through the register file
			begin
				REGISTER[i] = 8'b00000000; // Clearing each element in register array
			end
			
		end

		else if (WRITE == 1'b1)	// If the RESET signal is LOW, write to the registers if WRITE signal is HIGH
		begin
		
			#1 REGISTER[INADDRESS] = IN; // Assigns the input value IN to relevant register address after a delay of 1
			
		end
		
	end
	
	initial begin
			$monitor($time, "\t%d\t%d\t%d\t%d\t%d\t%d\t%d\t%d", REGISTER[0], REGISTER[1],REGISTER[2],REGISTER[3],REGISTER[4],REGISTER[5],REGISTER[6],REGISTER[7]);
	end

endmodule

PART1/Part3/cpu.v
/*
CO224: Computer Architecture 
Lab 05: Part-3				 
The CPU module			 
Group - 12					 
*/

`include "Alu.v"
`include "Reg_file.v"
`include "2sComp.v"
`include "Mux.v"


// cpu module definition
module cpu(PC, INSTRUCTION, CLK, RESET);

	// Begin port declaration
	input [31:0] INSTRUCTION;   // Declare inputs
	input CLK, RESET;           
	
	output reg [31:0] PC;       // Declare output
    // End of port declaration

	// Connections for Register File
	wire [2:0] READREG1, READREG2, WRITEREG;
	wire [7:0] REGOUT1, REGOUT2;
	reg WRITEENABLE;
	
	// Connections for ALU
	wire [7:0] OPERAND1, OPERAND2, ALURESULT;
	reg [2:0] ALUOP;
	
	// Connections for 2's Complemented MUX
	wire [7:0] TwosCompMuxOut;
	wire [7:0] TwosCompOperand;
	reg PositiveOrNegative;
	
	// Connections for immediate value MUX
	wire [7:0] IMMEDIATE;
	reg ImmOrRegistered;
	
	// PC value (Next instruction to be executed)
	reg [31:0] PC_Reg;
	
	// OPCODE stored in CPU
	reg [7:0] OPCODE;
	
    // Instantiation of modules
	reg_file MyRegFile(ALURESULT, REGOUT1, REGOUT2, WRITEREG, READREG1, READREG2, WRITEENABLE, CLK, RESET);
    TwosComp MyTwosComp(REGOUT2, TwosCompOperand);
    mux TwosCompMux(REGOUT2, TwosCompOperand, PositiveOrNegative, TwosCompMuxOut);
    mux ImmediateMux(TwosCompMuxOut, IMMEDIATE, ImmOrRegistered, OPERAND2);
	alu MyAlu(REGOUT1, OPERAND2, ALURESULT, ALUOP);

	/*
    Control Logic to The CPU
    */

	// PC Update
	always @ ( posedge CLK )
	begin
		if (RESET == 1'b1) 
		begin
			#1
			PC = 0;		// If RESET signal is HIGH, set PC to zero (Reset the program)
			PC_Reg = 0;
		end
		else 
        begin
            #1 
            PC = PC_Reg;		// Else, write new PC value (Write to PC)
        end 
	end
	
	
	// Update PC Register
	always @ ( PC )
	begin
		#1 PC_Reg = PC_Reg + 4;   // PC = PC+4
	end
	
	
	// The Instruction Format
	
	/****************************************************************
	*    OP-CODE    *      RD       *       RT      *     RS/IMM    *
	*    [31:24]    *    [23:16]    *     [15:8]    *      [7:0]    *
	*****************************************************************
	*               *               *                *              *
	*    OPCODE     *    WRITEREG   *    READREG1   *    READREG2   *
	*               *               *               *   IMMEDIATE   *
	****************************************************************/
	
	assign IMMEDIATE = INSTRUCTION[7:0];
	assign READREG2 = INSTRUCTION[7:0];
	assign READREG1 = INSTRUCTION[15:8];
	assign WRITEREG = INSTRUCTION[23:16];
	
	//Decoding the instruction
	always @ ( INSTRUCTION )
	begin
	
		OPCODE = INSTRUCTION[31:24];	// Mapping the opcode field of the instruction to OPCODE
		
		#1			// 1 Time Unit Delay for Decoding process
		
		case ( OPCODE )
		
			// loadi instruction
			8'b00000000:	begin
								PositiveOrNegative = 1'b0;		// Set sign select MUX to positive sign
								ImmOrRegistered = 1'b1;			// Set immediate select MUX to select immediate value
								ALUOP = 3'b000;					// Set ALU to forward
								WRITEENABLE = 1'b1;				// Enable writing to register
							end
		
			// mov instruction
			8'b00000001:	begin
								PositiveOrNegative = 1'b0;		// Set sign select MUX to positive sign
								ImmOrRegistered = 1'b0;			// Set immediate select MUX to select register input
								ALUOP = 3'b000;					// Set ALU to FORWARD
								WRITEENABLE = 1'b1;				// Enable writing to register
							end
			
			// add instruction
			8'b00000010:	begin
								PositiveOrNegative = 1'b0;		// Set sign select MUX to positive sign
								ImmOrRegistered = 1'b0;			// Set immediate select MUX to select register input
								ALUOP = 3'b001;					// Set ALU to ADD
								WRITEENABLE = 1'b1;				// Enable writing to register
							end	
		
			// sub instruction
			8'b00000011:	begin
								PositiveOrNegative = 1'b1;		// Set sign select MUX to negative sign
								ImmOrRegistered = 1'b0;			// Set immediate select MUX to select register input
								ALUOP = 3'b001;					// Set ALU to ADD
								WRITEENABLE = 1'b1;				// Enable writing to register
							end

			// and instruction
			8'b00000100:	begin
								PositiveOrNegative = 1'b0;		// Set sign select MUX to positive sign
								ImmOrRegistered = 1'b0;			// Set immediate select MUX to select register input
								ALUOP = 3'b010;					// Set ALU to AND
								WRITEENABLE = 1'b1;				// Enable writing to register
							end
							
			// or operation
			8'b00000101:	begin
								PositiveOrNegative = 1'b0;		// Set sign select MUX to positive sign
								ImmOrRegistered = 1'b0;			// Set immediate select MUX to select register input
								ALUOP = 3'b011;					// Set ALU to OR
								WRITEENABLE = 1'b1;				// Enable writing to register
							end

			// Don't Cares as default values
            default:	begin
							PositiveOrNegative = 1'bx;
							ImmOrRegistered = 1'bx;				
							ALUOP = 3'bxxx;			
							WRITEENABLE = 1'bx;		
						end

		endcase
		
	end
	
endmodule

PART1/Part5/cpu_tb.v
// Computer Architecture (CO224) - Lab 05
// Design: Testbench of Integrated CPU of Simple Processor
// Author: Isuru Nawinne

`include "cpu.v"



module cpu_tb;

    reg CLK, RESET;
    wire [31:0] PC;
    wire [31:0] INSTRUCTION;
    
    /* 
    ------------------------
     SIMPLE INSTRUCTION MEM
    ------------------------
    */
    
    // TODO: Initialize an array of registers (8x1024) named 'instr_mem' to be used as instruction memory
    reg [7:0] instr_mem [1023:0];
    
    // TODO: Create combinational logic to support CPU instruction fetching, given the Program Counter(PC) value 
    //       (make sure you include the delay for instruction fetching here)
    assign #2 INSTRUCTION = {instr_mem[PC+3], instr_mem[PC+2], instr_mem[PC+1], instr_mem[PC]};

    initial
    begin
        // Initialize instruction memory with the set of instructions you need execute on CPU
        
        // METHOD 1: manually loading instructions to instr_mem
        //{instr_mem[10'd3], instr_mem[10'd2], instr_mem[10'd1], instr_mem[10'd0]} = 32'b00000000000001000000000000000101;
        //{instr_mem[10'd7], instr_mem[10'd6], instr_mem[10'd5], instr_mem[10'd4]} = 32'b00000000000000100000000000001001;
        //{instr_mem[10'd11], instr_mem[10'd10], instr_mem[10'd9], instr_mem[10'd8]} = 32'b00000010000001100000010000000010;
        
        // METHOD 2: loading instr_mem content from instr_mem.mem file
        $readmemb("instr_mem.mem", instr_mem);
    end
    
    /* 
    -----
     CPU
    -----
    */
    cpu mycpu(PC, INSTRUCTION, CLK, RESET);

    initial
    begin
    
        // generate files needed to plot the waveform using GTKWave
        $dumpfile("cpu_wavedata.vcd");
		$dumpvars(0, cpu_tb);
        
        CLK = 1'b0;
        RESET = 1'b0;
        
        // TODO: Reset the CPU (by giving a pulse to RESET signal) to start the program execution
        RESET = 1'b1;
		#5
		RESET = 1'b0;
        
        // finish simulation after some time
        #500
        $finish;
        
    end
    
    // clock signal generation
    always
        #4 CLK = ~CLK;
        

endmodule

PART1/Part3/cpu_wavedata.vcd
$date
	Thu May 25 20:09:45 2023
$end
$version
	Icarus Verilog
$end
$timescale
	1s
$end
$scope module cpu_tb $end
$var wire 32 ! PC [31:0] $end
$var wire 32 " INSTRUCTION [31:0] $end
$var reg 1 # CLK $end
$var reg 1 $ RESET $end
$scope module mycpu $end
$var wire 1 # CLK $end
$var wire 32 % INSTRUCTION [31:0] $end
$var wire 1 $ RESET $end
$var wire 3 & WRITEREG [2:0] $end
$var wire 8 ' TwosCompOperand [7:0] $end
$var wire 8 ( TwosCompMuxOut [7:0] $end
$var wire 8 ) REGOUT2 [7:0] $end
$var wire 8 * REGOUT1 [7:0] $end
$var wire 3 + READREG2 [2:0] $end
$var wire 3 , READREG1 [2:0] $end
$var wire 8 - OPERAND2 [7:0] $end
$var wire 8 . IMMEDIATE [7:0] $end
$var wire 8 / ALURESULT [7:0] $end
$var reg 3 0 ALUOP [2:0] $end
$var reg 1 1 ImmOrRegistered $end
$var reg 8 2 OPCODE [7:0] $end
$var reg 32 3 PC [31:0] $end
$var reg 32 4 PC_Reg [31:0] $end
$var reg 1 5 PositiveOrNegative $end
$var reg 1 6 WRITEENABLE $end
$scope module ImmediateMux $end
$var wire 8 7 IN2 [7:0] $end
$var wire 1 1 SELECT $end
$var wire 8 8 IN1 [7:0] $end
$var reg 8 9 OUT [7:0] $end
$upscope $end
$scope module MyAlu $end
$var wire 8 : DATA2 [7:0] $end
$var wire 3 ; SELECT [2:0] $end
$var wire 8 < Or_Out [7:0] $end
$var wire 8 = Forward_Out [7:0] $end
$var wire 8 > DATA1 [7:0] $end
$var wire 8 ? And_Out [7:0] $end
$var wire 8 @ Add_Out [7:0] $end
$var reg 8 A RESULT [7:0] $end
$scope module add1 $end
$var wire 8 B DATA2 [7:0] $end
$var wire 8 C RESULT [7:0] $end
$var wire 8 D DATA1 [7:0] $end
$upscope $end
$scope module and1 $end
$var wire 8 E DATA2 [7:0] $end
$var wire 8 F RESULT [7:0] $end
$var wire 8 G DATA1 [7:0] $end
$upscope $end
$scope module forward1 $end
$var wire 8 H DATA2 [7:0] $end
$var wire 8 I RESULT [7:0] $end
$upscope $end
$scope module or1 $end
$var wire 8 J DATA2 [7:0] $end
$var wire 8 K RESULT [7:0] $end
$var wire 8 L DATA1 [7:0] $end
$upscope $end
$upscope $end
$scope module MyRegFile $end
$var wire 1 # CLK $end
$var wire 8 M IN [7:0] $end
$var wire 3 N INADDRESS [2:0] $end
$var wire 8 O OUT1 [7:0] $end
$var wire 3 P OUT1ADDRESS [2:0] $end
$var wire 8 Q OUT2 [7:0] $end
$var wire 3 R OUT2ADDRESS [2:0] $end
$var wire 1 $ RESET $end
$var wire 1 6 WRITE $end
$var integer 32 S i [31:0] $end
$upscope $end
$scope module MyTwosComp $end
$var wire 8 T OPERAND [7:0] $end
$var wire 8 U RESULT [7:0] $end
$upscope $end
$scope module TwosCompMux $end
$var wire 8 V IN1 [7:0] $end
$var wire 8 W IN2 [7:0] $end
$var wire 1 5 SELECT $end
$var reg 8 X OUT [7:0] $end
$upscope $end
$upscope $end
$upscope $end
$enddefinitions $end
#0
$dumpvars
bx X
bx W
bx V
bx U
bx T
bx S
bx R
bx Q
bx P
bx O
bx N
bx M
bx L
bx K
bx J
bx I
bx H
bx G
bx F
bx E
bx D
bx C
bx B
bx A
bx @
bx ?
bx >
bx =
bx <
bx ;
bx :
bx 9
bx 8
bx 7
x6
x5
bx 4
bx 3
bx 2
x1
bx 0
bx /
bx .
bx -
bx ,
bx +
bx *
bx )
bx (
bx '
bx &
bx %
1$
0#
bx "
bx !
$end
#4
1#
#5
b1000 S
b0 4
b0 !
b0 3
0$
#6
b100 4
#7
b0 ,
b0 P
b101 -
b101 9
b101 :
b101 B
b101 E
b101 H
b101 J
b101 +
b101 R
b0 &
b0 N
b0 2
b101 .
b101 7
b101 "
b101 %
#8
b101 /
b101 A
b101 M
b0x0x ?
b0x0x F
bx1x1 <
bx1x1 K
b101 =
b101 I
16
b0 0
b0 ;
11
05
0#
#9
b0 (
b0 8
b0 X
b0 *
b0 >
b0 D
b0 G
b0 L
b0 O
b0 )
b0 Q
b0 T
b0 V
#10
b101 <
b101 K
b0 ?
b0 F
b0 '
b0 U
b0 W
#11
b101 @
b101 C
#12
1#
#13
b100 !
b100 3
#14
b1000 4
#15
b1001 -
b1001 9
b1001 :
b1001 B
b1001 E
b1001 H
b1001 J
b1 +
b1 R
b1 &
b1 N
b1001 .
b1001 7
b10000000000001001 "
b10000000000001001 %
b101 *
b101 >
b101 D
b101 G
b101 L
b101 O
#16
b1001 /
b1001 A
b1001 M
b1101 <
b1101 K
b1001 =
b1001 I
b1 ?
b1 F
0#
#17
b1110 @
b1110 C
#20
1#
#21
b1000 !
b1000 3
#22
b1100 4
#23
b1 -
b1 9
b1 :
b1 B
b1 E
b1 H
b1 J
b10 &
b10 N
b1001 (
b1001 8
b1001 X
b1 2
b1 .
b1 7
b1001 )
b1001 Q
b1001 T
b1001 V
b1000000100000000000000001 "
b1000000100000000000000001 %
#24
b1 /
b1 A
b1 M
b1001 -
b1001 9
b1001 :
b1001 B
b1001 E
b1001 H
b1001 J
b101 <
b101 K
b1 =
b1 I
b11110111 '
b11110111 U
b11110111 W
01
0#
#25
b1001 /
b1001 A
b1001 M
b1101 <
b1101 K
b1001 =
b1001 I
#28
1#
#29
b1100 !
b1100 3
#30
b10000 4
#31
b10 ,
b10 P
b0 +
b0 R
b11 &
b11 N
b10 2
b0 .
b0 7
b10000000110000001000000000 "
b10000000110000001000000000 %
#32
b1110 /
b1110 A
b1110 M
b1 0
b1 ;
0#
#33
b101 -
b101 9
b101 :
b101 B
b101 E
b101 H
b101 J
b101 (
b101 8
b101 X
b1001 *
b1001 >
b1001 D
b1001 G
b1001 L
b1001 O
b101 )
b101 Q
b101 T
b101 V
#34
b101 =
b101 I
b11111011 '
b11111011 U
b11111011 W
#36
1#
#37
b10000 !
b10000 3
#38
b10100 4
#39
b11 ,
b11 P
b1 +
b1 R
b100 &
b100 N
b11 2
b1 .
b1 7
b11000001000000001100000001 "
b11000001000000001100000001 %
#40
b11111011 -
b11111011 9
b11111011 :
b11111011 B
b11111011 E
b11111011 H
b11111011 J
b11111011 (
b11111011 8
b11111011 X
15
0#
#41
b1001 ?
b1001 F
b11111011 <
b11111011 K
b11111011 =
b11111011 I
b1110 *
b1110 >
b1110 D
b1110 G
b1110 L
b1110 O
b1001 )
b1001 Q
b1001 T
b1001 V
#42
b11110111 -
b11110111 9
b11110111 :
b11110111 B
b11110111 E
b11110111 H
b11110111 J
b11110111 (
b11110111 8
b11110111 X
b11111111 <
b11111111 K
b1010 ?
b1010 F
b11110111 '
b11110111 U
b11110111 W
#43
b110 ?
b110 F
b11110111 =
b11110111 I
#44
b101 /
b101 A
b101 M
b101 @
b101 C
1#
#45
b10100 !
b10100 3
#46
b11000 4
#47
b0 ,
b0 P
b101 +
b101 R
b0 &
b0 N
b0 2
b1110101 .
b1110101 7
b1110101 "
b1110101 %
#48
b11110111 /
b11110111 A
b11110111 M
b1110101 -
b1110101 9
b1110101 :
b1110101 B
b1110101 E
b1110101 H
b1110101 J
b1001 (
b1001 8
b1001 X
b0 0
b0 ;
11
05
0#
#49
b1110101 /
b1110101 A
b1110101 M
b0 (
b0 8
b0 X
b100 ?
b100 F
b1111111 <
b1111111 K
b1110101 =
b1110101 I
b101 *
b101 >
b101 D
b101 G
b101 L
b101 O
b0 )
b0 Q
b0 T
b0 V
#50
b1110101 <
b1110101 K
b101 ?
b101 F
b0 '
b0 U
b0 W
#51
b1111010 @
b1111010 C
#52
1#
#53
b11000 !
b11000 3
#54
b11100 4
#55
b10010010 -
b10010010 9
b10010010 :
b10010010 B
b10010010 E
b10010010 H
b10010010 J
b10 +
b10 R
b1 &
b1 N
b10010010 .
b10010010 7
b1110101 *
b1110101 >
b1110101 D
b1110101 G
b1110101 L
b1110101 O
b10000000010010010 "
b10000000010010010 %
#56
b10010010 /
b10010010 A
b10010010 M
b11110111 <
b11110111 K
b10010010 =
b10010010 I
b10000 ?
b10000 F
0#
#57
b1001 (
b1001 8
b1001 X
b1001 )
b1001 Q
b1001 T
b1001 V
b111 @
b111 C
#58
b11110111 '
b11110111 U
b11110111 W
#60
1#
#61
b11100 !
b11100 3
#62
b100000 4
#63
b1 ,
b1 P
b0 -
b0 9
b0 :
b0 B
b0 E
b0 H
b0 J
b0 +
b0 R
b101 &
b101 N
b100 2
b0 .
b0 7
b100000001010000000100000000 "
b100000001010000000100000000 %
#64
b0 /
b0 A
b0 M
b1001 -
b1001 9
b1001 :
b1001 B
b1001 E
b1001 H
b1001 J
b0 ?
b0 F
b1110101 <
b1110101 K
b0 =
b0 I
b10 0
b10 ;
01
0#
#65
b1110101 -
b1110101 9
b1110101 :
b1110101 B
b1110101 E
b1110101 H
b1110101 J
b1 /
b1 A
b1 M
b1110101 (
b1110101 8
b1110101 X
b1 ?
b1 F
b1111101 <
b1111101 K
b1001 =
b1001 I
b10010010 *
b10010010 >
b10010010 D
b10010010 G
b10010010 L
b10010010 O
b1110101 )
b1110101 Q
b1110101 T
b1110101 V
#66
b10000 /
b10000 A
b10000 M
b1110101 =
b1110101 I
b11110111 <
b11110111 K
b10000 ?
b10000 F
b10001011 '
b10001011 U
b10001011 W
#68
1#
#69
b100000 !
b100000 3
#70
b100100 4
#71
b101 ,
b101 P
b10 +
b10 R
b110 &
b110 N
b101 2
b10 .
b10 7
b101000001100000010100000010 "
b101000001100000010100000010 %
#72
b11110111 /
b11110111 A
b11110111 M
b11 0
b11 ;
0#
#73
b1001 -
b1001 9
b1001 :
b1001 B
b1001 E
b1001 H
b1001 J
b1001 (
b1001 8
b1001 X
b10000 *
b10000 >
b10000 D
b10000 G
b10000 L
b10000 O
b1001 )
b1001 Q
b1001 T
b1001 V
#74
b11001 /
b11001 A
b11001 M
b0 ?
b0 F
b1001 =
b1001 I
b11001 <
b11001 K
b11110111 '
b11110111 U
b11110111 W
#75
b11001 @
b11001 C
#76
1#
#77
b100100 !
b100100 3
#78
b101000 4
#79
bx ,
bx P
bx +
bx R
bx &
bx N
bx 2
bx .
bx 7
bx "
bx %
#80
bx -
bx 9
bx :
bx B
bx E
bx H
bx J
b11110111 (
b11110111 8
b11110111 X
x6
bx 0
bx ;
x1
x5
0#
#81
b0x0000 ?
b0x0000 F
bx1xxxx <
bx1xxxx K
bx =
bx I
bx *
bx >
bx D
bx G
bx L
bx O
bx )
bx Q
bx T
bx V
#82
bx (
bx 8
bx X
bx <
bx K
bx ?
bx F
bx '
bx U
bx W
bx @
bx C
#84
1#
#85
b101000 !
b101000 3
#86
b101100 4
#88
0#
#92
1#
#93
b101100 !
b101100 3
#94
b110000 4
#96
0#
#100
1#
#101
b110000 !
b110000 3
#102
b110100 4
#104
0#
#108
1#
#109
b110100 !
b110100 3
#110
b111000 4
#112
0#
#116
1#
#117
b111000 !
b111000 3
#118
b111100 4
#120
0#
#124
1#
#125
b111100 !
b111100 3
#126
b1000000 4
#128
0#
#132
1#
#133
b1000000 !
b1000000 3
#134
b1000100 4
#136
0#
#140
1#
#141
b1000100 !
b1000100 3
#142
b1001000 4
#144
0#
#148
1#
#149
b1001000 !
b1001000 3
#150
b1001100 4
#152
0#
#156
1#
#157
b1001100 !
b1001100 3
#158
b1010000 4
#160
0#
#164
1#
#165
b1010000 !
b1010000 3
#166
b1010100 4
#168
0#
#172
1#
#173
b1010100 !
b1010100 3
#174
b1011000 4
#176
0#
#180
1#
#181
b1011000 !
b1011000 3
#182
b1011100 4
#184
0#
#188
1#
#189
b1011100 !
b1011100 3
#190
b1100000 4
#192
0#
#196
1#
#197
b1100000 !
b1100000 3
#198
b1100100 4
#200
0#
#204
1#
#205
b1100100 !
b1100100 3
#206
b1101000 4
#208
0#
#212
1#
#213
b1101000 !
b1101000 3
#214
b1101100 4
#216
0#
#220
1#
#221
b1101100 !
b1101100 3
#222
b1110000 4
#224
0#
#228
1#
#229
b1110000 !
b1110000 3
#230
b1110100 4
#232
0#
#236
1#
#237
b1110100 !
b1110100 3
#238
b1111000 4
#240
0#
#244
1#
#245
b1111000 !
b1111000 3
#246
b1111100 4
#248
0#
#252
1#
#253
b1111100 !
b1111100 3
#254
b10000000 4
#256
0#
#260
1#
#261
b10000000 !
b10000000 3
#262
b10000100 4
#264
0#
#268
1#
#269
b10000100 !
b10000100 3
#270
b10001000 4
#272
0#
#276
1#
#277
b10001000 !
b10001000 3
#278
b10001100 4
#280
0#
#284
1#
#285
b10001100 !
b10001100 3
#286
b10010000 4
#288
0#
#292
1#
#293
b10010000 !
b10010000 3
#294
b10010100 4
#296
0#
#300
1#
#301
b10010100 !
b10010100 3
#302
b10011000 4
#304
0#
#308
1#
#309
b10011000 !
b10011000 3
#310
b10011100 4
#312
0#
#316
1#
#317
b10011100 !
b10011100 3
#318
b10100000 4
#320
0#
#324
1#
#325
b10100000 !
b10100000 3
#326
b10100100 4
#328
0#
#332
1#
#333
b10100100 !
b10100100 3
#334
b10101000 4
#336
0#
#340
1#
#341
b10101000 !
b10101000 3
#342
b10101100 4
#344
0#
#348
1#
#349
b10101100 !
b10101100 3
#350
b10110000 4
#352
0#
#356
1#
#357
b10110000 !
b10110000 3
#358
b10110100 4
#360
0#
#364
1#
#365
b10110100 !
b10110100 3
#366
b10111000 4
#368
0#
#372
1#
#373
b10111000 !
b10111000 3
#374
b10111100 4
#376
0#
#380
1#
#381
b10111100 !
b10111100 3
#382
b11000000 4
#384
0#
#388
1#
#389
b11000000 !
b11000000 3
#390
b11000100 4
#392
0#
#396
1#
#397
b11000100 !
b11000100 3
#398
b11001000 4
#400
0#
#404
1#
#405
b11001000 !
b11001000 3
#406
b11001100 4
#408
0#
#412
1#
#413
b11001100 !
b11001100 3
#414
b11010000 4
#416
0#
#420
1#
#421
b11010000 !
b11010000 3
#422
b11010100 4
#424
0#
#428
1#
#429
b11010100 !
b11010100 3
#430
b11011000 4
#432
0#
#436
1#
#437
b11011000 !
b11011000 3
#438
b11011100 4
#440
0#
#444
1#
#445
b11011100 !
b11011100 3
#446
b11100000 4
#448
0#
#452
1#
#453
b11100000 !
b11100000 3
#454
b11100100 4
#456
0#
#460
1#
#461
b11100100 !
b11100100 3
#462
b11101000 4
#464
0#
#468
1#
#469
b11101000 !
b11101000 3
#470
b11101100 4
#472
0#
#476
1#
#477
b11101100 !
b11101100 3
#478
b11110000 4
#480
0#
#484
1#
#485
b11110000 !
b11110000 3
#486
b11110100 4
#488
0#
#492
1#
#493
b11110100 !
b11110100 3
#494
b11111000 4
#496
0#
#500
1#
#501
b11111000 !
b11111000 3
#502
b11111100 4
