PART1/Part1/Or.v
/*
CO224: Computer Architecture 
Lab 05: Part-1				 
The Sub Module OR			 
Group - 12					 
*/

// OR module definition
module OR(DATA1, DATA2, RESULT);

	// Begin port declaration
	input [7:0] DATA1, DATA2; // Declare inputs
	
	output [7:0] RESULT; // Declare output
	// End of port declaration
	
	// Using continuous assignment assign DATA1 | DATA2 to RESULT (Unit's delay = #1)
	assign #1 RESULT = DATA1 | DATA2;
	
endmodule

PART1/Part4/And.v
/*
CO224: Computer Architecture 
Lab 05: Part-1				 
The Sub Module AND			 
Group - 12					 
*/

// AND module definition
module AND(DATA1, DATA2, RESULT);

	// Begin port declaration
	input [7:0] DATA1, DATA2; // Declare inputs
	
	output [7:0] RESULT; // Declare output
	// End of port declaration

	// Using continuous assignment assign DATA1 & DATA2 to RESULT (Unit's delay = #1)
	assign #1 RESULT = DATA1 & DATA2;
	
endmodule

PART1/Part2/Add.v
/*
CO224: Computer Architecture 
Lab 05: Part-1				 
The Sub Module ADD			 
Group - 12					 
*/

// ADD module definition
module ADD(DATA1, DATA2, RESULT);

	// Begin port declaration
	input [7:0] DATA1, DATA2; // Declare inputs
	
	output [7:0] RESULT; // Declare output
	// End of port declaration
	
	// Using continuous assignment assign DATA1 + DATA2 to RESULT (Unit's delay = #2)
	assign #2 RESULT = DATA1 + DATA2;
	
endmodule

PART2/Part1/Forward.v
/*
CO224: Computer Architecture 
Lab 05: Part-1				 
The Sub Module FORWARD			 
Group - 12					 
*/

// FORWARD module definition
module FORWARD(DATA2, RESULT);

	// Begin port declaration
	input [7:0] DATA2; // Declare inputs
	
	output [7:0] RESULT; // Declare output
	// End of port declaration
	
	// Using continuous assignment assign DATA2 to RESULT (Unit's delay = #1)
	assign #1 RESULT = DATA2;

endmodule

PART1/Part1/Alu.v
/*
CO224: Computer Architecture 
Lab 05: Part-1				 
The ALU Module			 
Group - 12					 
*/

// Importing modules
`include "Add.v"
`include "And.v"
`include "Forward.v"
`include "Or.v"

// ALU module definition
module alu(DATA1, DATA2, RESULT, SELECT);
	
	// Begin port declaration

	// Declare inputs
	input [7:0] DATA1, DATA2;
	input [2:0] SELECT;
	
	// Declare output
	output reg [7:0] RESULT;

	// End of port declaration
	
	// Wires for outputs of the distinct functional units
	wire [7:0] Forward_Out, Add_Out, And_Out, Or_Out;
	
	
	// Instantiation of modules
	FORWARD forward1(DATA2, Forward_Out); // Instantiate a FORWARD object
	ADD add1(DATA1, DATA2, Add_Out); // Instantiate an ADD object
	AND and1(DATA1, DATA2, And_Out); // Instantiate an AND object
	OR or1(DATA1, DATA2, Or_Out); // Instantiate an OR object
	
	
	// A MUX to pick one of the functional units, outputs and send it to RESULT based on the SELECT value
	always @ (Forward_Out, Add_Out, And_Out, Or_Out, SELECT)	
	begin

		case (SELECT)	
			3'b000 :	RESULT = Forward_Out;	//SELECT = 0 : FORWARD
			3'b001 :	RESULT = Add_Out;		//SELECT = 1 : ADD
			3'b010 :	RESULT = And_Out;		//SELECT = 2 : AND
			3'b011 :	RESULT = Or_Out;		//SELECT = 3 : OR
			3'b1xx :	RESULT = 8'bxxxxxxxx;	//SELECT = 1xx : x
		endcase

	end

endmodule

PART1/Part1/testbench.v
/*
CO224: Computer Architecture 
Lab 05: Part-1				 
The testbench module			 
Group - 12					 
*/

// Importing modules
`include "Alu.v"

// Definition of testbench module
module testbench;

	// Input ports for ALU
	reg [7:0] OPERAND1, OPERAND2;
	reg [2:0] ALUOP;
	
	// Output port of ALU
	wire [7:0] ALURESULT;
	
	// Instantiate an ALU instance
	alu ALU1(OPERAND1, OPERAND2, ALURESULT, ALUOP);
	
	//Simulation

	initial begin

		OPERAND1 = 0;	
		OPERAND2 = 0;
		
		#5

		// The FORWARD operation
		OPERAND1 = 10;	
		OPERAND2 = 20;
		ALUOP = 0;

		#5
		
		// The ADD operation
		OPERAND2 = 15;
		ALUOP = 1;
		
		#5
		
		// The AND operation
		OPERAND1 = 7;
		OPERAND2 = 14;
		ALUOP = 2;
		
		#5
		
		// The OR operation
		OPERAND2 = 30;
		ALUOP = 3;
		
	end
	
	// Monitoring the changes and dumping the wave data into a vcd file
	initial begin
		$dumpfile("wavedata.vcd");
		$dumpvars(0, ALU1);
		$monitor($time, " OPERAND1 = %d OPERAND2 = %d ALUOP = %b ALURESULT = %d", OPERAND1, OPERAND2, ALUOP, ALURESULT);
		#30 $finish;
	end

endmodule

PART1/Part1/wavedata.vcd
$date
	Tue May 23 18:45:59 2023
$end
$version
	Icarus Verilog
$end
$timescale
	1s
$end
$scope module testbench $end
$scope module ALU1 $end
$var wire 8 ! DATA1 [7:0] $end
$var wire 8 " DATA2 [7:0] $end
$var wire 3 # SELECT [2:0] $end
$var wire 8 $ Or_Out [7:0] $end
$var wire 8 % Forward_Out [7:0] $end
$var wire 8 & And_Out [7:0] $end
$var wire 8 ' Add_Out [7:0] $end
$var reg 8 ( RESULT [7:0] $end
$scope module add1 $end
$var wire 8 ) DATA1 [7:0] $end
$var wire 8 * DATA2 [7:0] $end
$var wire 8 + RESULT [7:0] $end
$upscope $end
$scope module and1 $end
$var wire 8 , DATA1 [7:0] $end
$var wire 8 - DATA2 [7:0] $end
$var wire 8 . RESULT [7:0] $end
$upscope $end
$scope module forward1 $end
$var wire 8 / DATA2 [7:0] $end
$var wire 8 0 RESULT [7:0] $end
$upscope $end
$scope module or1 $end
$var wire 8 1 DATA1 [7:0] $end
$var wire 8 2 DATA2 [7:0] $end
$var wire 8 3 RESULT [7:0] $end
$upscope $end
$upscope $end
$upscope $end
$enddefinitions $end
#0
$dumpvars
bx 3
b0 2
b0 1
bx 0
b0 /
bx .
b0 -
b0 ,
bx +
b0 *
b0 )
bx (
bx '
bx &
bx %
bx $
bx #
b0 "
b0 !
$end
#1
b0 $
b0 3
b0 &
b0 .
b0 %
b0 0
#2
b0 '
b0 +
#5
b0 (
b0 #
b10100 "
b10100 *
b10100 -
b10100 /
b10100 2
b1010 !
b1010 )
b1010 ,
b1010 1
#6
b10100 (
b11110 $
b11110 3
b10100 %
b10100 0
#7
b11110 '
b11110 +
#10
b11110 (
b1 #
b1111 "
b1111 *
b1111 -
b1111 /
b1111 2
#11
b1010 &
b1010 .
b1111 $
b1111 3
b1111 %
b1111 0
#12
b11001 (
b11001 '
b11001 +
#15
b1010 (
b10 #
b1110 "
b1110 *
b1110 -
b1110 /
b1110 2
b111 !
b111 )
b111 ,
b111 1
#16
b110 (
b110 &
b110 .
b1110 %
b1110 0
#17
b10101 '
b10101 +
#20
b1111 (
b11 #
b11110 "
b11110 *
b11110 -
b11110 /
b11110 2
#21
b11111 (
b11111 $
b11111 3
b11110 %
b11110 0
#22
b100101 '
b100101 +
